CORScanner/.gitignore
CORScanner/LICENSE
CORScanner/__init__.py
CORScanner/cors_scan.py
CORScanner/origins.json
CORScanner/requirements.txt
CORScanner/top_100_domains.txt
CORScanner/.github/workflows/python-publish.yml
CORScanner/common/__init__.py
CORScanner/common/common.py
CORScanner/common/corscheck.py
CORScanner/common/logger.py
CORScanner/images/screenshot.png
CORScanner/images/walmart.png
cors-1.0.1.dist-info/METADATA
cors-1.0.1.dist-info/WHEEL
cors-1.0.1.dist-info/entry_points.txt
cors-1.0.1.dist-info/top_level.txt
cors-1.0.1.dist-info/RECORD
